grrproc/__about__.py
grrproc/__init__.py
grrproc/grp.py
grrproc-2.0.0.dist-info/LICENSE
grrproc-2.0.0.dist-info/METADATA
grrproc-2.0.0.dist-info/WHEEL
grrproc-2.0.0.dist-info/top_level.txt
grrproc-2.0.0.dist-info/RECORD
