Metadata-Version: 2.1
Name: grrproc
Version: 2.0.0
Summary: Python project to follow r-process nucleosynthesis graphically.
Home-page: https://github.com/mengkel/grrproc
Author: Clemson University
Author-email: mengkel@g.clemson.edu
License: GPLv3+
Project-URL: Bug Reports, https://github.com/mengkel/grrproc/issues
Project-URL: Source, https://github.com/mengkel/grrproc/
Keywords: nuclear physics astronomy
Classifier: Development Status :: 4 - Beta
Classifier: Intended Audience :: Science/Research
Classifier: Topic :: Scientific/Engineering :: Astronomy
Classifier: License :: OSI Approved :: GNU General Public License v3 or later (GPLv3+)
Classifier: Programming Language :: Python :: 3
License-File: LICENSE
Requires-Dist: wnnet
